typeid/__init__.py
typeid/sqla.py
typeid-1.0.0.dist-info/LICENSE
typeid-1.0.0.dist-info/METADATA
typeid-1.0.0.dist-info/WHEEL
typeid-1.0.0.dist-info/RECORD
