Metadata-Version: 2.1
Name: typeid
Version: 1.0.0
Summary: UUID-compatible Typed IDs with prefixes
License: MIT
Author: Fabian Schuh
Author-email: info@chainsquad.com
Requires-Python: >=3.10,<4.0
Classifier: License :: OSI Approved :: MIT License
Classifier: Programming Language :: Python :: 3
Classifier: Programming Language :: Python :: 3.10
Classifier: Programming Language :: Python :: 3.11
Classifier: Programming Language :: Python :: 3.12
Requires-Dist: base58 (>=2.1.1,<3.0.0)
